python_ftp_server/__init__.py
python_ftp_server/__main__.py
python_ftp_server/ftp_server.py
python_ftp_server-1.3.18.dist-info/METADATA
python_ftp_server-1.3.18.dist-info/WHEEL
python_ftp_server-1.3.18.dist-info/top_level.txt
python_ftp_server-1.3.18.dist-info/RECORD
